pyside6_qml_stubgen/__init__.py
pyside6_qml_stubgen/__main__.py
pyside6_qml_stubgen/_version.py
pyside6_qml_stubgen/dirty_file_detection.py
pyside6_qml_stubgen/py.typed
pyside6_qml_stubgen/pyside_patching.py
pyside6_qml_stubgen/qmlregistrar_types.py
pyside6_qml_stubgen-0.1.0a9.dist-info/METADATA
pyside6_qml_stubgen-0.1.0a9.dist-info/WHEEL
pyside6_qml_stubgen-0.1.0a9.dist-info/entry_points.txt
pyside6_qml_stubgen-0.1.0a9.dist-info/licenses/LICENCE.md
pyside6_qml_stubgen-0.1.0a9.dist-info/RECORD
