Metadata-Version: 2.4
Name: pyside6-qml-stubgen
Version: 0.1.0a9
Summary: Generate QML stub files (.qmltypes) from Python modules (which use PySide6)
Project-URL: Homepage, https://github.com/matsjoyce/pyside6-qml-stubgen
Project-URL: Repository, https://github.com/matsjoyce/pyside6-qml-stubgen.git
Project-URL: Issues, https://github.com/matsjoyce/pyside6-qml-stubgen/issues
Author: Matthew Joyce
License-File: LICENCE.md
Keywords: pyside6,qml,qt6,type checking
Classifier: Development Status :: 4 - Beta
Classifier: Environment :: X11 Applications :: Qt
Classifier: Intended Audience :: Developers
Classifier: License :: OSI Approved :: GNU Lesser General Public License v3 or later (LGPLv3+)
Classifier: Programming Language :: Python :: 3
Classifier: Programming Language :: Python :: 3.10
Classifier: Programming Language :: Python :: 3.11
Classifier: Programming Language :: Python :: 3.12
Classifier: Topic :: Software Development :: Build Tools
Classifier: Topic :: Software Development :: Quality Assurance
Requires-Python: >=3.10
Requires-Dist: docopt
Requires-Dist: pydantic>=2
Requires-Dist: pyside6>=6.4
Provides-Extra: dev
Requires-Dist: black; extra == 'dev'
Requires-Dist: build; extra == 'dev'
Requires-Dist: mypy; extra == 'dev'
Requires-Dist: pytest; extra == 'dev'
Requires-Dist: pytest-cov; extra == 'dev'
Requires-Dist: types-docopt; extra == 'dev'
